Coodhi_Scrapper/__init__.py
Coodhi_Scrapper/config.py
Coodhi_Scrapper/exceptions.py
Coodhi_Scrapper/functions.py
Coodhi_Scrapper/transfermarkt.py
coodhi_scrapper-1.0.0.dist-info/licenses/LICENSE
coodhi_scrapper-1.0.0.dist-info/METADATA
coodhi_scrapper-1.0.0.dist-info/WHEEL
coodhi_scrapper-1.0.0.dist-info/top_level.txt
coodhi_scrapper-1.0.0.dist-info/RECORD
