Metadata-Version: 2.4
Name: Coodhi_Scrapper
Version: 1.0.0
Summary: Package for scraping soccer data from a variety of sources.
Author: Victor Vimos
Author-email: vvimos@coodhi.com
License:                     GNU GENERAL PUBLIC LICENSE
Project-URL: Homepage, https://github.com/VektorMachine/Coodhi_Scraper_Pypi
Project-URL: Repository, https://github.com/VektorMachine/Coodhi_Scraper_Pypi
Project-URL: BugTracker, https://github.com/VektorMachine/Coodhi_Scraper_Pypi/issues
Keywords: webscraping,scraping,soccer,football,soccer data,football data,English Premier League,La Liga,Bundesliga,Serie A,Ligue 1,Champions League,World Cup
Classifier: License :: OSI Approved :: GNU General Public License v3 (GPLv3)
Classifier: Programming Language :: Python :: 3.9
Classifier: Programming Language :: Python :: 3.10
Classifier: Programming Language :: Python :: 3.11
Classifier: Programming Language :: Python :: 3.12
Classifier: Operating System :: OS Independent
Requires-Python: >=3.9
License-File: LICENSE
Requires-Dist: botasaurus>=4.0.76
Requires-Dist: bs4>=0.0.2
Requires-Dist: cloudscraper>=1.2.71
Requires-Dist: datetime>=5.5
Requires-Dist: lxml>=5.3.0
Requires-Dist: numpy>=2.0.2
Requires-Dist: pandas>=2.2.3
Requires-Dist: pyyaml>=6.0.2
Requires-Dist: requests>=2.32.3
Requires-Dist: rootutils>=1.0.7
Requires-Dist: selenium>=4.28.1
Requires-Dist: tqdm>=4.67.1
Provides-Extra: test
Requires-Dist: pytest>=8.3.4; extra == "test"
Requires-Dist: pytest-cov>=6.0.0; extra == "test"
Provides-Extra: docs
Requires-Dist: furo>=2024.8.6; extra == "docs"
Requires-Dist: myst-nb>=1.1.2; extra == "docs"
Requires-Dist: sphinx>=7.4.7; extra == "docs"
Provides-Extra: build
Requires-Dist: build>=1.2.2.post1; extra == "build"
Requires-Dist: setuptools>=75.8.0; extra == "build"
Requires-Dist: wheel>=0.45.1; extra == "build"
Provides-Extra: publish
Requires-Dist: publish>=0.3.6; extra == "publish"
Provides-Extra: dev
Requires-Dist: marimo>=0.14.16; extra == "dev"
Requires-Dist: tox>=4.24.1; extra == "dev"
Provides-Extra: typecheck
Requires-Dist: pandas-stubs>=2.2.2.240807; extra == "typecheck"
Requires-Dist: types-beautifulsoup4>=4.12.0.20241020; extra == "typecheck"
Requires-Dist: types-openpyxl>=3.1.5.20241225; extra == "typecheck"
Requires-Dist: types-python-dateutil>=2.9.0.20241206; extra == "typecheck"
Requires-Dist: types-requests>=2.32.0.20241016; extra == "typecheck"
Requires-Dist: types-tqdm>=4.67.0.20241221; extra == "typecheck"
Requires-Dist: types-pyyaml>=6.0.12.20250516; extra == "typecheck"
Requires-Dist: mypy>=1.14.1; extra == "typecheck"
Provides-Extra: lint
Requires-Dist: ruff>=0.11.10; extra == "lint"
Dynamic: license-file
